libfcs/transforms.py
libfcs/gates.py
libfcs/_libfcs_ext.cpython-38-x86_64-linux-gnu.so
libfcs/__init__.py
libfcs/events.py
libfcs/exceptions.py
libfcs.libs/libgmp-afec2dd4.so.10.2.0
libfcs.libs/liblibfcs-39221037.so
libfcs.libs/libffi-af4ed708.so.6.0.1
libfcs-0.0.2.dist-info/top_level.txt
libfcs-0.0.2.dist-info/LICENSE
libfcs-0.0.2.dist-info/METADATA
libfcs-0.0.2.dist-info/RECORD
libfcs-0.0.2.dist-info/WHEEL
