Metadata-Version: 2.1
Name: libfcs
Version: 0.0.2
Home-page: https://github.com/meson800/libfcs-python
Author: Christopher Johnstone
Author-email: meson800@gmail.com
License: MIT
Classifier: Development Status :: 2 - Pre-Alpha
Classifier: Programming Language :: Python :: 3
Classifier: License :: OSI Approved :: GNU General Public License v2 or later (GPLv2+)
Classifier: Operating System :: OS Independent
Requires-Python: >=3.7
License-File: LICENSE
Requires-Dist: numpy (>=1.16)
